LICENSE
MANIFEST.in
README.rst
setup.py
djexcept/__init__.py
djexcept/config.py
djexcept/exceptions.py
djexcept/handlers.py
djexcept/middleware.py
djexcept/registration.py
djexcept/util.py
djexcept.egg-info/PKG-INFO
djexcept.egg-info/SOURCES.txt
djexcept.egg-info/dependency_links.txt
djexcept.egg-info/requires.txt
djexcept.egg-info/top_level.txt