Metadata-Version: 1.1
Name: djexcept
Version: 0.1.3
Summary: Flexible and versatile exception handling for django.
Home-page: https://github.com/efficiosoft/djexcept
Author: Robert Schindler
Author-email: r.schindler@efficiosoft.com
License: GPL-3
Platform: UNKNOWN
Classifier: Development Status :: 5 - Production/Stable
Classifier: Framework :: Django
Classifier: Intended Audience :: Developers
Classifier: License :: OSI Approved :: GNU General Public License (GPL)
Classifier: Natural Language :: English
Classifier: Operating System :: OS Independent
Classifier: Programming Language :: Python
Classifier: Topic :: Software Development :: Libraries :: Python Modules
